<openerp>
	<data>
		<!-- Campaign Followups -->

		<record model="ir.ui.view" id="view_lead_automation_campaign_form">
			<field name="name">lead.automation.campaign.form</field>
			<field name="model">lead.automation.campaign</field>
			<field name="arch" type="xml">
				<form string="Lead Automation Campaign">
					<header>
						<button name="running" type="workflow" string="Run" states="draft" class="oe_highlight"/>
						<button name="done" type="workflow" string="Done" states="running" class="oe_highlight"/>
						<button name="draft" type="workflow" string="Set to Draft" states="done,cancelled"/>
						<button name="cancelled" type="workflow" string="Cancel Campaign" states="running"/>
						<field name="state" readonly="1" widget="statusbar" statusbar_visible="draft,running,done"/>
					</header>
					<sheet string="Campaign">
						<div class="oe_title">
							<label for="name" class="oe_edit_only"/>
							<h1><field name="name" class="oe_inline"/></h1>
						</div>
						<group>
							<group>
								<field name="mode"/>
								<field name="fixed_cost"/>
								<field name="segments_count" readonly="1"/>
							</group>
							<group>
								<field name="object_id"/>
								<field name="partner_field_id"/>
								<field name="unique_field_id"/>
							</group>
						</group>
						<separator string="Activities"/>
						<field name="activity_ids" context="{'default_object_id': object_id, 'default_campaign_id': active_id}"/>
					</sheet>
				</form>
			</field>
		</record>

		<record model="ir.ui.view" id="view_lead_automation_campaign_tree">
			<field name="name">lead.automation.campaign.tree</field>
			<field name="model">lead.automation.campaign</field>
			<field name="arch" type="xml">
				<tree colors="blue:state == 'draft';black:state == 'running';gray:state in ('done','cancelled')" string="Campaigns">
					<field name="name"/>
					<field name="object_id"/>
					<field name="mode"/>
					<!-- 					<field name="fixed_cost"/> -->
					<field name="state"/>
				</tree>
			</field>
		</record>

		<record model="ir.actions.act_window" id="action_lead_automation_campaign_form">
			<field name="name">Campaigns</field>
			<field name="type">ir.actions.act_window</field>
			<field name="res_model">lead.automation.campaign</field>
			<field name="view_type">form</field>
			<field name="view_mode">tree,form</field>
			<field name="view_id" ref="view_lead_automation_campaign_tree"/>
			<field name="context">{'group_by': []}</field>
			<!-- 			<field name="search_view_id" ref="view_lead_automation_campaign_search"/> -->
			<field name="help" type="html">
				<p class="oe_view_nocontent_create">
					Click to create a marketing campaign.
				</p><p>
				Odoo's marketing campaign allows you to automate communication
				to your prospects. You can define a segment (set of conditions) on
				your leads and partners to fullfil the campaign.
				</p><p>
				A campaign can have many activities like sending an email, printing
				a letter, assigning to a team, etc. These activities are triggered
				from specific situations; contact form, 10 days after first
				contact, if a lead is not closed yet, etc.
				</p>
			</field>
		</record>
	</data>
</openerp>
